<?xml version="1.0" encoding="UTF-8"?>

<!--
	boolean StructDelete(structure, key [, indicatenotexisting ])
-->
<function xmlns="http://www.cfeclipse.org/version1/dictionary"
	name="structdelete" returns="boolean">
	<help><![CDATA[
		Removes an element from a structure.
	]]></help>
	<parameter name="structure" type="String" required="true">
		<help><![CDATA[
			Structure or a variable that contains one. Contains element
			to remove
		]]></help>
	</parameter>
	<parameter name="key" type="String" required="true">
		<help><![CDATA[
			Element to remove
		]]></help>
	</parameter>
	<parameter name="indicatenotexisting" type="boolean" required="false">
		<help><![CDATA[
		]]></help>
		<values default="false">
			<value option="true" />
			<value option="false" />
		</values>
	</parameter>
</function>
